path_loader_auto.pth
path_loader/__init__.py
path_loader/loader.py
path_loader-0.1.1.dist-info/licenses/LICENSE
path_loader-0.1.1.dist-info/METADATA
path_loader-0.1.1.dist-info/WHEEL
path_loader-0.1.1.dist-info/entry_points.txt
path_loader-0.1.1.dist-info/top_level.txt
path_loader-0.1.1.dist-info/RECORD
