Metadata-Version: 2.4
Name: path-loader
Version: 0.1.1
Summary: 自動從配置檔載入 Python 路徑到 sys.path
Author: Pyan-X
License-Expression: MIT
Project-URL: Repository, https://github.com/Pyan-X/path-loader
Keywords: path,sys.path,pythonpath,auto-load
Classifier: Programming Language :: Python :: 3
Classifier: Programming Language :: Python :: 3.7
Classifier: Programming Language :: Python :: 3.8
Classifier: Programming Language :: Python :: 3.9
Classifier: Programming Language :: Python :: 3.10
Classifier: Programming Language :: Python :: 3.11
Classifier: Programming Language :: Python :: 3.12
Requires-Python: >=3.7
License-File: LICENSE
Dynamic: license-file
